Workbook
Name Semaglutide_net_benefit_q2: DCEA!$D$8
Name slimstatin_net_benefit_q2: DCEA!$D$8
Name Q1_P: benefit!$C$6
Name total_opportunity_cost_q5: oppcost!$G$7
Name mean_benefit: CEA!$C$7
Name total_opportunity_cost_q4: oppcost!$F$7
Name qale_baseline_q3: DCEA!$E$6
Name nice_threshold: CEA!$C$9
Name qale_baseline_q1: DCEA!$C$6
Name ce_threshold: CEA!$C$8
Name drug_costs: CEA!$C$5
Name opp_cost_q1: oppcost!$C$6
Name Q1_pop_share: benefit!$C$7
Name qale_slimstatin_q1: DCEA!$C$10
Name qale_slimstatin_q4: DCEA!$F$10
Name total_opportunity_cost_q1: oppcost!$C$7
Name Q3_P: benefit!$E$6
Name qale_slimstatin_mean: DCEA!$H$10
Name nice_theshold: CEA!$C$9
Name absolute_gap_Semaglutide: DCEA!$I$10
Name Semaglutide_net_benefit_q3: DCEA!$E$8
Name opp_cost_q4: oppcost!$F$6
Name opp_cost_pc_q3: oppcost!$E$4
Name slimstatin_benefit_q2: benefit!$D$10
Name slimstatin_benefit_q5: benefit!$G$10
Name total_opportunity_cost_q2: oppcost!$D$7
Name net_cost_pp: CEA!$C$4
Name Semaglutide_net_benefit_q1: DCEA!$C$8
Name slimstatin_benefit_q4: benefit!$F$10
Name opp_cost_pc_q2: oppcost!$D$4
Name Semaglutide_benefit_q1: benefit!$C$10
Name Semaglutide_benefit_q5: benefit!$G$10
Name qale_baseline_mean: DCEA!$H$6
Name opp_cost_q5: oppcost!$G$6
Name opp_cost_pc_q1: oppcost!$C$4
Name slimstatin_net_benefit_q1: DCEA!$C$8
Name Q5_pop: benefit!$G$7
Name qale_Semaglutide_q4: DCEA!$F$10
Name drug_cost: CEA!$C$4
Name total_treated: benefit!$H$9
Name absolute_gap_baseline: DCEA!$I$6
Name absolute_gap_slimstatin: DCEA!$I$10
Name opp_cost_pc_q5: oppcost!$G$4
Name Q2_pop_share: benefit!$C$7
Name threshold: CEA!$C$8
Name Semaglutide_net_benefit_q5: DCEA!$G$8
Name QALY: CEA!$C$4
Name qale_Semaglutide_q3: DCEA!$E$10
Name Q4_pop: benefit!$F$7
Name total_opportunity_cost_q3: oppcost!$E$7
Name qale_slimstatin_q5: DCEA!$G$10
Name slimstatin_net_benefit_q4: DCEA!$F$8
Name qale_Semaglutide_q2: DCEA!$D$10
Name Q1_pop: benefit!$C$7
Name Semaglutide_benefit_q4: benefit!$F$10
Name qale_Semaglutide_mean: DCEA!$H$10
Name qale_Semaglutide_q5: DCEA!$G$10
Name slimstatin_net_benefit_q5: DCEA!$G$8
Name qale_baseline_q5: DCEA!$G$6
Name Semaglutide_benefit_q3: benefit!$E$10

Sheet Summary
B1: DCEA: Semaglutide for Obesity in England
B2: Summary Table
B4: Parameter | E4: Value
B5: Incremental QALY per patient | E5: 0.098
B6: Net cost per patient | E6: £1,601
B7: ICER | E7: £16,337
B8: Cost-effective at £20,000 (NICE)? | E8: Yes
B9: Cost-effective at £12,936 (empirical)? | E9: No
B10: Total net benefit @ £20,000 | E10: +273.6 QALYs
B11: Total net benefit @ £12,936 | E11: −392.7 QALYs
B12: Net benefit : poorest quintile (Q1) | E12: −210.6 QALYs
B13: Net benefit : richest quintile (Q5) | E13: +380.9 QALYs
B14: Equity verdict | E14: Regressive under pro-rich uptake
B15: Headline | E15: Cost-effective overall, but transfers net health from the poorest three quintiles to the richest two.

Sheet Notes & Sources
A1: Notes & Sources
A4: Data sources:
A7: 1 | B7: Baseline QALE by IMD quintile, Love-Koh et al. (2023), PharmacoEconomics
A8: 2 | B8: Opportunity-cost distribution, miqdadasaria/DCEA repo, net_health_benefits_universal_distribution.csv, commit e8c482e (Nov 2019)
A10: 3 | B10: Thresholds = £20,000/QALY (NICE base case); £12,936/QALY (Claxton et al. 2015, empirical)
A11: 4 | B11: DCEA framework = Asaria, Griffin & Cookson (2016), Medical Decision Making
A12: 5 | B12: Comparator study = Malcolm et al., YHEC/Novo Nordisk (DCEA of semaglutide, HPR58)
A14: Key conventions:
A17: 1 | B17: Per-person vs total: baseline QALE and net-benefit-per-person are per-individual; opportunity cost, patients treated, and total net benefit are population totals. Convert only by × or ÷ population.
A20: 2 | B20: Opportunity cost: total displaced = net cost × patients treated ÷ threshold, distributed across quintiles by chosen share.
A22: 3 | B22: Welfare: Atkinson equally-distributed equivalent (EDE) on post-drug QALE across inequality-aversion levels.

Sheet CEA
B1: Cost-Effectiveness Analysis: Semaglutide
B3: Parameter | C3: Value
B4: Incremental QALY per patient | C4: 0.098
B5: Net cost per patient | C5: 1601
B6: ICER | C6: =C5/C4 -> 16336.735
B7: Acceptability threshold | C7: 20000
B8: Opportunity cost threshold (empirical) | C8: 12936
B9: Opportunity cost threshold (NICE convention) | C9: 20000
B10: NHB at £20,000 | C10: =C4-(C5/C9) -> 0.01795
B11: NHB at £12,936 | C11: =C4-(C5/C8) -> -0.025763142
B13: =IF(C10>0, "✓ Cost-effective at £20,000", "✗ Not cost-effective at £20,000") -> ✓ Cost-effective at £20,000
B14: =IF(C11>0, "✓ Cost-effective at £12,936", "✗ Not cost-effective at £12,936") -> ✗ Not cost-effective at £12,936

Sheet benefit
B1: Benefit Incidence by Income Quintile
B3: Parameter | C3: Q1 (Poorest) | D3: Q2 | E3: Q3 | F3: Q4 | G3: Q5 (Richest)
B4: Obesity prevalence (BMI≥30) | C4: 0.38 | D4: 0.33 | E4: 0.29 | F4: 0.26 | G4: 0.25
B5: Eligible prevalence (BMI≥35) | C5: =C4*0.25 -> 0.095 | D5: =D4*0.25 -> 0.0825 | E5: =E4*0.25 -> 0.0725 | F5: =F4*0.25 -> 0.065 | G5: =G4*0.25 -> 0.0625
B6: Population | C6: 8982727 | D6: 9687031 | E6: 9744766 | F6: 9530611 | G6: 9275464
B7: Population shares | C7: =C6/SUM(C6:G6) -> 0.19022899 | D7: =D6/SUM(C6:G6) -> 0.20514418 | E7: =E6/SUM(C6:G6) -> 0.20636684 | F7: =F6/SUM(C6:G6) -> 0.20183164 | G7: =G6/SUM(C6:G6) -> 0.19642834 | H7: =SUM(C7:G7) -> 1
B8: Uptake gradient | C8: 0.0004 | D8: 0.002 | E8: 0.0034 | F8: 0.0073 | G8: 0.011
B9: Patients treated | C9: =C6*C5*C8 -> 341.34363 | D9: =D6*D5*D8 -> 1598.3601 | E9: =E6*E5*E8 -> 2402.0848 | F9: =F6*F5*F8 -> 4522.2749 | G9: =G6*G5*G8 -> 6376.8815 | H9: =SUM(C9:G9) -> 15240.945
B10: Total QALYs | C10: =C9*0.098 -> 33.451675 | D10: =D9*0.098 -> 156.63929 | E10: =E9*0.098 -> 235.40431 | F10: =F9*0.098 -> 443.18294 | G10: =G9*0.098 -> 624.93439

Sheet oppcost
B1: Opportunity Cost by Income Quintile
B3: Parameter | C3: Q1 (Poorest) | D3: Q2 | E3: Q3 | F3: Q4 | G3: Q5 (Richest)
B4: Scenario 1 (NICE Base Case - Flat) | C4: 0.2 | D4: 0.2 | E4: 0.2 | F4: 0.2 | G4: 0.2
B5: Scenario 2 (Sensitivity Testing - Asaria-Github) | C5: 0.2437 | D5: 0.2115 | E5: 0.2151 | F5: 0.1756 | G5: 0.1541
B6: S1 - Opportunity cost per person (QALYs) | C6: {=(drug_costs * total_treated) / nice_threshold * (C4 / Q1_P)} -> 2.7164082e-05 | D6: {=(drug_costs * total_treated) / nice_threshold * (D4 / Q2_P)} -> 2.5189093e-05 | E6: {=(drug_costs * total_treated) / nice_threshold * (E4 / Q3_P)} -> 2.5039855e-05 | F6: {=(drug_costs * total_treated) / nice_threshold * (F4 / Q4_P)} -> 2.5602506e-05 | G6: {=(drug_costs * total_treated) / nice_threshold * (G4 / Q5_P)} -> 2.6306773e-05
B7: S1 - Total opportunity cost (QALYs) | C7: {=C6*Q1_P} -> 244.00753 | D7: {=D6*Q2_P} -> 244.00753 | E7: {=E6*Q3_P} -> 244.00753 | F7: {=F6*Q4_P} -> 244.00753 | G7: {=G6*Q5_P} -> 244.00753
B8: S2 - Opportunity cost per person (QALYs) | C8: {=(drug_costs * total_treated) / nice_threshold * (C5 / Q1_P)} -> 3.3099433e-05 | D8: {=(drug_costs * total_treated) / nice_threshold * (D5 / Q2_P)} -> 2.6637466e-05 | E8: {=(drug_costs * total_treated) / nice_threshold * (E5 / Q3_P)} -> 2.6930364e-05 | F8: {=(drug_costs * total_treated) / nice_threshold * (F5 / Q4_P)} -> 2.2479001e-05 | G8: {=(drug_costs * total_treated) / nice_threshold * (G5 / Q5_P)} -> 2.0269369e-05
B9: S2 - Total opportunity cost (QALYs) | C9: {=C8*Q1_P} -> 297.32317 | D9: {=D8*Q2_P} -> 258.03796 | E9: {=E8*Q3_P} -> 262.4301 | F9: {=F8*Q4_P} -> 214.23861 | G9: {=G8*Q5_P} -> 188.0078
B11: To capture the socioeconomic distribution of health opportunity cost, the base case applies a flat distribution (20% per quintile), with a non-flat empirical gradient examined in sensitivity analysis — following established DCEA practice, in which displacement is assumed flat as a neutral base case and a regressive gradient is tested separately. The gradient is taken from the University of York DCEA web tool repository (Asaria, miqdadasaria/DCEA), specifically the file net_health_benefits_universal_distribution.csv at commit e8c482e ("updated opportunity cost weights", November 2019), which reports opportunity-cost weights disaggregated by region (North/South) and IMD quintile. As these weights are shares summing to one across all ten region–quintile cells, the two regional entries were summed within each IMD quintile to collapse the distribution to five national quintile shares: 24.37% (Q1, most deprived), 21.15% (Q2), 21.51% (Q3), 17.56% (Q4) and 15.41% (Q5, least deprived). This reproduces the empirical pattern whereby marginal NHS disinvestment displaces proportionally more health among more deprived groups, who consume greater publicly funded resources after adjustment for clinical need. The minor Q2–Q3 inversion is retained as a faithful feature of the source's regional structure rather than smoothed.

Sheet DCEA
B1: Distributional Cost-Effectiveness Analysis (DCEA): Semaglutide
B4: Quality-Adjusted Life Expectancy (QALE) by Quintile
B5: Measure | C5: Q1 (Poorest) | D5: Q2 | E5: Q3 | F5: Q4 | G5: Q5 (Richest) | H5: Mean/Total | I5: Inequality
B6: baseline QALE at birth | C6: 63 | D6: 68 | E6: 70 | F6: 73 | G6: 75 | H6: =AVERAGE(C6:G6) -> 69.8 | I6: =qale_baseline_q5-qale_baseline_q1 -> 12
B8: net benefit (QALYs) | C8: {=(benefit!C10 - oppcost!C7)/Q1_P} -> -2.3440082e-05 | D8: {=(benefit!D10 - oppcost!D7)/Q2_P} -> -9.0190935e-06 | E8: {=(benefit!E10 - oppcost!E7)/Q3_P} -> -8.8285515e-07 | F8: {=(benefit!F10 - oppcost!F7)/Q4_P} -> 2.0898494e-05 | G8: {=(benefit!G10 - oppcost!G7)/Q5_P} -> 4.1068227e-05 | H8: =SUM(C8:G8) -> 2.862469e-05
B10: Semaglutide QALE at birth | C10: =C6+C8 -> 62.999977 | D10: =D6+D8 -> 67.999991 | E10: =E6+E8 -> 69.999999 | F10: =F6+F8 -> 73.000021 | G10: =G6+G8 -> 75.000041 | H10: =AVERAGE(C10:G10) -> 69.800006 | I10: {=qale_Semaglutide_q5-qale_Semaglutide_q1} -> 12.000065
B12: total net benefit (QALYs) | C12: {=C8*Q1_P} -> -210.55585 | D12: {=Semaglutide_net_benefit_q2*Q2_P} -> -87.368238 | E12: {=Semaglutide_net_benefit_q3*Q3_P} -> -8.6032169 | F12: {=Semaglutide_net_benefit_q4*Q4_P} -> 199.17541 | G12: {=Semaglutide_net_benefit_q5*Q5_P} -> 380.92686 | H12: =SUM(C12:G12) -> 273.57496
B14: Relative Net Benefit Index | C14: =(C12/ benefit!C6) + 1 -> 0.99997656 | D14: =(D12/ benefit!D6) + 1 -> 0.99999098 | E14: =(E12/ benefit!E6) + 1 -> 0.99999912 | F14: =(F12/ benefit!F6) + 1 -> 1.0000209 | G14: =(G12/ benefit!G6) + 1 -> 1.0000411
E15: /?
B16: Social Welfare by Inequality Aversion (α)
B17: Inequality Aversion (α) | C17: Baseline | D17: Semaglutide | E17: Preferred Option
B18: inequality aversion | C18: baseline | D18: Semaglutide | E18: social welfare maximising decision
B19: 0 | C19: {=( SUMPRODUCT(benefit!$C$7:$G$7, $C$6:$G$6^(1-B19)) )^(1/(1-B19))} -> 69.845745 | D19: {=( SUMPRODUCT(benefit!$C$7:$G$7, $C$10:$G$10^(1-B19)) )^(1/(1-B19))} -> 69.845751 | E19: =IF(C19>D19,"baseline",IF(C19<D19,"semaglutide","indifferent")) -> semaglutide
B20: 0.1 | C20: {=( SUMPRODUCT(benefit!$C$7:$G$7, $C$6:$G$6^(1-B20)) )^(1/(1-B20))} -> 69.83356 | D20: {=( SUMPRODUCT(benefit!$C$7:$G$7, $C$10:$G$10^(1-B20)) )^(1/(1-B20))} -> 69.833566 | E20: =IF(C20>D20,"baseline",IF(C20<D20,"semaglutide","indifferent")) -> semaglutide
B21: 0.2 | C21: {=( SUMPRODUCT(benefit!$C$7:$G$7, $C$6:$G$6^(1-B21)) )^(1/(1-B21))} -> 69.821351 | D21: {=( SUMPRODUCT(benefit!$C$7:$G$7, $C$10:$G$10^(1-B21)) )^(1/(1-B21))} -> 69.821357 | E21: =IF(C21>D21,"baseline",IF(C21<D21,"semaglutide","indifferent")) -> semaglutide
B22: 0.3 | C22: {=( SUMPRODUCT(benefit!$C$7:$G$7, $C$6:$G$6^(1-B22)) )^(1/(1-B22))} -> 69.809118 | D22: {=( SUMPRODUCT(benefit!$C$7:$G$7, $C$10:$G$10^(1-B22)) )^(1/(1-B22))} -> 69.809124 | E22: =IF(C22>D22,"baseline",IF(C22<D22,"semaglutide","indifferent")) -> semaglutide
B23: 0.4 | C23: {=( SUMPRODUCT(benefit!$C$7:$G$7, $C$6:$G$6^(1-B23)) )^(1/(1-B23))} -> 69.796861 | D23: {=( SUMPRODUCT(benefit!$C$7:$G$7, $C$10:$G$10^(1-B23)) )^(1/(1-B23))} -> 69.796867 | E23: =IF(C23>D23,"baseline",IF(C23<D23,"semaglutide","indifferent")) -> semaglutide
B24: 0.5 | C24: {=( SUMPRODUCT(benefit!$C$7:$G$7, $C$6:$G$6^(1-B24)) )^(1/(1-B24))} -> 69.784581 | D24: {=( SUMPRODUCT(benefit!$C$7:$G$7, $C$10:$G$10^(1-B24)) )^(1/(1-B24))} -> 69.784586 | E24: =IF(C24>D24,"baseline",IF(C24<D24,"semaglutide","indifferent")) -> semaglutide
B25: 0.6 | C25: {=( SUMPRODUCT(benefit!$C$7:$G$7, $C$6:$G$6^(1-B25)) )^(1/(1-B25))} -> 69.772277 | D25: {=( SUMPRODUCT(benefit!$C$7:$G$7, $C$10:$G$10^(1-B25)) )^(1/(1-B25))} -> 69.772282 | E25: =IF(C25>D25,"baseline",IF(C25<D25,"semaglutide","indifferent")) -> semaglutide
B26: 0.7 | C26: {=( SUMPRODUCT(benefit!$C$7:$G$7, $C$6:$G$6^(1-B26)) )^(1/(1-B26))} -> 69.75995 | D26: {=( SUMPRODUCT(benefit!$C$7:$G$7, $C$10:$G$10^(1-B26)) )^(1/(1-B26))} -> 69.759955 | E26: =IF(C26>D26,"baseline",IF(C26<D26,"semaglutide","indifferent")) -> semaglutide
B27: 0.8 | C27: {=( SUMPRODUCT(benefit!$C$7:$G$7, $C$6:$G$6^(1-B27)) )^(1/(1-B27))} -> 69.747601 | D27: {=( SUMPRODUCT(benefit!$C$7:$G$7, $C$10:$G$10^(1-B27)) )^(1/(1-B27))} -> 69.747605 | E27: =IF(C27>D27,"baseline",IF(C27<D27,"semaglutide","indifferent")) -> semaglutide
B28: 0.9 | C28: {=( SUMPRODUCT(benefit!$C$7:$G$7, $C$6:$G$6^(1-B28)) )^(1/(1-B28))} -> 69.735228 | D28: {=( SUMPRODUCT(benefit!$C$7:$G$7, $C$10:$G$10^(1-B28)) )^(1/(1-B28))} -> 69.735233 | E28: =IF(C28>D28,"baseline",IF(C28<D28,"semaglutide","indifferent")) -> semaglutide
B29: 1 | C29: {=EXP( SUMPRODUCT(benefit!$C$7:$G$7, LN($C$6:$G$6)) )} -> 69.722833 | D29: {=EXP( SUMPRODUCT(benefit!$C$7:$G$7, LN($C$10:$G$10)) )} -> 69.722837 | E29: =IF(C29>D29,"baseline",IF(C29<D29,"semaglutide","indifferent")) -> semaglutide
B30: 1.5 | C30: {=( SUMPRODUCT(benefit!$C$7:$G$7, $C$6:$G$6^(1-B30)) )^(1/(1-B30))} -> 69.660526 | D30: {=( SUMPRODUCT(benefit!$C$7:$G$7, $C$10:$G$10^(1-B30)) )^(1/(1-B30))} -> 69.66053 | E30: =IF(C30>D30,"baseline",IF(C30<D30,"semaglutide","indifferent")) -> semaglutide
B31: 2 | C31: {=( SUMPRODUCT(benefit!$C$7:$G$7, $C$6:$G$6^(1-B31)) )^(1/(1-B31))} -> 69.597688 | D31: {=( SUMPRODUCT(benefit!$C$7:$G$7, $C$10:$G$10^(1-B31)) )^(1/(1-B31))} -> 69.597691 | E31: =IF(C31>D31,"baseline",IF(C31<D31,"semaglutide","indifferent")) -> semaglutide
B32: 2.5 | C32: {=( SUMPRODUCT(benefit!$C$7:$G$7, $C$6:$G$6^(1-B32)) )^(1/(1-B32))} -> 69.534348 | D32: {=( SUMPRODUCT(benefit!$C$7:$G$7, $C$10:$G$10^(1-B32)) )^(1/(1-B32))} -> 69.534351 | E32: =IF(C32>D32,"baseline",IF(C32<D32,"semaglutide","indifferent")) -> semaglutide
B33: 3 | C33: {=( SUMPRODUCT(benefit!$C$7:$G$7, $C$6:$G$6^(1-B33)) )^(1/(1-B33))} -> 69.470536 | D33: {=( SUMPRODUCT(benefit!$C$7:$G$7, $C$10:$G$10^(1-B33)) )^(1/(1-B33))} -> 69.470538 | E33: =IF(C33>D33,"baseline",IF(C33<D33,"semaglutide","indifferent")) -> semaglutide
B34: 5 | C34: {=( SUMPRODUCT(benefit!$C$7:$G$7, $C$6:$G$6^(1-B34)) )^(1/(1-B34))} -> 69.211244 | D34: {=( SUMPRODUCT(benefit!$C$7:$G$7, $C$10:$G$10^(1-B34)) )^(1/(1-B34))} -> 69.211243 | E34: =IF(C34>D34,"baseline",IF(C34<D34,"semaglutide","indifferent")) -> baseline
B35: 10 | C35: {=( SUMPRODUCT(benefit!$C$7:$G$7, $C$6:$G$6^(1-B35)) )^(1/(1-B35))} -> 68.548174 | D35: {=( SUMPRODUCT(benefit!$C$7:$G$7, $C$10:$G$10^(1-B35)) )^(1/(1-B35))} -> 68.548167 | E35: =IF(C35>D35,"baseline",IF(C35<D35,"semaglutide","indifferent")) -> baseline

Sheet sensitivity analysis
B1: Sensitivity Analysis: Semaglutide DCEA
B4: SA1 — Drug Cost (base case: £1,601 per year)
B6: Drug Cost (£/yr) | C6: ICER (£/QALY) | D6: QALE Q1 | E6: QALE Q2 | F6: QALE Q3 | G6: QALE Q4 | H6: QALE Q5 | I6: Social Welfare Semaglutide | J6: Decision at α=0.5
B7: 1400 | C7: =B7 / CEA!$C$4 -> 14285.714 | D7: =benefit!C10 - ($B7*benefit!$H$9 / CEA!$C$7) * oppcost!C4 -> -179.92155 | E7: =benefit!D10 - ($B7*benefit!$H$9 / CEA!$C$7) * oppcost!D4 -> -56.733938 | F7: =benefit!E10 - ($B7*benefit!$H$9 / CEA!$C$7) * oppcost!E4 -> 22.031083 | G7: =benefit!F10 - ($B7*benefit!$H$9 / CEA!$C$7) * oppcost!F4 -> 229.80971 | H7: =benefit!G10 - ($B7*benefit!$H$9 / CEA!$C$7) * oppcost!G4 -> 411.56116 | I7: =((0.2*(63+(D7/8982727))^(0.5)+0.2*(68+(E7/9687031))^(0.5)+0.2*(70+(F7/9744766))^(0.5)+0.2*(73+(G7/9530611))^(0.5)+0.2*(75+(H7/9275464))^(0.5))^(1/0.5))-69.784581 -> -0.047632333 | J7: =IF(I7>0, "semaglutide", "baseline") -> baseline
B8: 1601 | C8: =B8 / CEA!$C$4 -> 16336.735 | D8: =benefit!C10 - ($B8*benefit!$H$9 / CEA!$C$7) * oppcost!C4 -> -210.55585 | E8: =benefit!D10 - ($B8*benefit!$H$9 / CEA!$C$7) * oppcost!D4 -> -87.368238 | F8: =benefit!E10 - ($B8*benefit!$H$9 / CEA!$C$7) * oppcost!E4 -> -8.6032169 | G8: =benefit!F10 - ($B8*benefit!$H$9 / CEA!$C$7) * oppcost!F4 -> 199.17541 | H8: =benefit!G10 - ($B8*benefit!$H$9 / CEA!$C$7) * oppcost!G4 -> 380.92686 | I8: =((0.2*(63+(D8/8982727))^(0.5)+0.2*(68+(E8/9687031))^(0.5)+0.2*(70+(F8/9744766))^(0.5)+0.2*(73+(G8/9530611))^(0.5)+0.2*(75+(H8/9275464))^(0.5))^(1/0.5))-69.784581 -> -0.047635584 | J8: =IF(I8>0, "semaglutide", "baseline") -> baseline
B9: 2000 | C9: =B9 / CEA!$C$4 -> 20408.163 | D9: =benefit!C10 - ($B9 * benefit!$H$9 / CEA!$C$7) * oppcost!C4 -> -271.36722 | E9: =benefit!D10 - ($B9 * benefit!$H$9 / CEA!$C$7) * oppcost!D4 -> -148.17961 | F9: =benefit!E10 - ($B9 * benefit!$H$9 / CEA!$C$7) * oppcost!E4 -> -69.414587 | G9: =benefit!F10 - ($B9 * benefit!$H$9 / CEA!$C$7) * oppcost!F4 -> 138.36404 | H9: =benefit!G10 - ($B9 * benefit!$H$9 / CEA!$C$7) * oppcost!G4 -> 320.11549 | I9: =((0.2*(63+(D9/8982727))^(0.5)+0.2*(68+(E9/9687031))^(0.5)+0.2*(70+(F9/9744766))^(0.5)+0.2*(73+(G9/9530611))^(0.5)+0.2*(75+(H9/9275464))^(0.5))^(1/0.5))-69.784581 -> -0.047642038 | J9: =IF(I9>0, "semaglutide", "baseline") -> baseline
B10: 4000 | C10: =B10 / CEA!$C$4 -> 40816.327 | D10: =benefit!C10 - ($B10 * benefit!$H$9 / CEA!$C$7) * oppcost!C4 -> -576.18612 | E10: =benefit!D10 - ($B10 * benefit!$H$9 / CEA!$C$7) * oppcost!D4 -> -452.99851 | F10: =benefit!E10 - ($B10 * benefit!$H$9 / CEA!$C$7) * oppcost!E4 -> -374.23349 | G10: =benefit!F10 - ($B10 * benefit!$H$9 / CEA!$C$7) * oppcost!F4 -> -166.45486 | H10: =benefit!G10 - ($B10 * benefit!$H$9 / CEA!$C$7) * oppcost!G4 -> 15.296588 | I10: =((0.2*(63+(D10/8982727))^(0.5)+0.2*(68+(E10/9687031))^(0.5)+0.2*(70+(F10/9744766))^(0.5)+0.2*(73+(G10/9530611))^(0.5)+0.2*(75+(H10/9275464))^(0.5))^(1/0.5))-69.784581 -> -0.047674385 | J10: =IF(I10>0, "semaglutide", "baseline") -> baseline
B11: 6000 | C11: =B11 / CEA!$C$4 -> 61224.49 | D11: =benefit!C10 - ($B11 * benefit!$H$9 / CEA!$C$7) * oppcost!C4 -> -881.00502 | E11: =benefit!D10 - ($B11 * benefit!$H$9 / CEA!$C$7) * oppcost!D4 -> -757.81741 | F11: =benefit!E10 - ($B11 * benefit!$H$9 / CEA!$C$7) * oppcost!E4 -> -679.05239 | G11: =benefit!F10 - ($B11 * benefit!$H$9 / CEA!$C$7) * oppcost!F4 -> -471.27376 | H11: =benefit!G10 - ($B11 * benefit!$H$9 / CEA!$C$7) * oppcost!G4 -> -289.52231 | I11: =((0.2*(63+(D11/8982727))^(0.5)+0.2*(68+(E11/9687031))^(0.5)+0.2*(70+(F11/9744766))^(0.5)+0.2*(73+(G11/9530611))^(0.5)+0.2*(75+(H11/9275464))^(0.5))^(1/0.5))-69.784581 -> -0.047706733 | J11: =IF(I11>0, "semaglutide", "baseline") -> baseline
B12: 8000 | C12: =B12 / CEA!$C$4 -> 81632.653 | D12: =benefit!C10 - ($B12 * benefit!$H$9 / CEA!$C$7) * oppcost!C4 -> -1185.8239 | E12: =benefit!D10 - ($B12 * benefit!$H$9 / CEA!$C$7) * oppcost!D4 -> -1062.6363 | F12: =benefit!E10 - ($B12 * benefit!$H$9 / CEA!$C$7) * oppcost!E4 -> -983.87129 | G12: =benefit!F10 - ($B12 * benefit!$H$9 / CEA!$C$7) * oppcost!F4 -> -776.09266 | H12: =benefit!G10 - ($B12 * benefit!$H$9 / CEA!$C$7) * oppcost!G4 -> -594.34121 | I12: =((0.2*(63+(D12/8982727))^(0.5)+0.2*(68+(E12/9687031))^(0.5)+0.2*(70+(F12/9744766))^(0.5)+0.2*(73+(G12/9530611))^(0.5)+0.2*(75+(H12/9275464))^(0.5))^(1/0.5))-69.784581 -> -0.047739081 | J12: =IF(I12>0, "semaglutide", "baseline") -> baseline
B13: 10000 | C13: =B13 / CEA!$C$4 -> 102040.82 | D13: =benefit!C10 - ($B13 * benefit!$H$9 / CEA!$C$7) * oppcost!C4 -> -1490.6428 | E13: =benefit!D10 - ($B13 * benefit!$H$9 / CEA!$C$7) * oppcost!D4 -> -1367.4552 | F13: =benefit!E10 - ($B13 * benefit!$H$9 / CEA!$C$7) * oppcost!E4 -> -1288.6902 | G13: =benefit!F10 - ($B13 * benefit!$H$9 / CEA!$C$7) * oppcost!F4 -> -1080.9116 | H13: =benefit!G10 - ($B13 * benefit!$H$9 / CEA!$C$7) * oppcost!G4 -> -899.16011 | I13: =((0.2*(63+(D13/8982727))^(0.5)+0.2*(68+(E13/9687031))^(0.5)+0.2*(70+(F13/9744766))^(0.5)+0.2*(73+(G13/9530611))^(0.5)+0.2*(75+(H13/9275464))^(0.5))^(1/0.5))-69.784581 -> -0.047771429 | J13: =IF(I13>0, "semaglutide", "baseline") -> baseline
B14: 15000 | C14: =B14 / CEA!$C$4 -> 153061.22 | D14: =benefit!C10 - ($B14 * benefit!$H$9 / CEA!$C$7) * oppcost!C4 -> -2252.6901 | E14: =benefit!D10 - ($B14 * benefit!$H$9 / CEA!$C$7) * oppcost!D4 -> -2129.5025 | F14: =benefit!E10 - ($B14 * benefit!$H$9 / CEA!$C$7) * oppcost!E4 -> -2050.7374 | G14: =benefit!F10 - ($B14 * benefit!$H$9 / CEA!$C$7) * oppcost!F4 -> -1842.9588 | H14: =benefit!G10 - ($B14 * benefit!$H$9 / CEA!$C$7) * oppcost!G4 -> -1661.2074 | I14: =((0.2*(63+(D14/8982727))^(0.5)+0.2*(68+(E14/9687031))^(0.5)+0.2*(70+(F14/9744766))^(0.5)+0.2*(73+(G14/9530611))^(0.5)+0.2*(75+(H14/9275464))^(0.5))^(1/0.5))-69.784581 -> -0.047852298 | J14: =IF(I14>0, "semaglutide", "baseline") -> baseline
B15: 20000 | C15: =B15 / CEA!$C$4 -> 204081.63 | D15: =benefit!C10 - ($B15 * benefit!$H$9 / CEA!$C$7) * oppcost!C4 -> -3014.7373 | E15: =benefit!D10 - ($B15 * benefit!$H$9 / CEA!$C$7) * oppcost!D4 -> -2891.5497 | F15: =benefit!E10 - ($B15 * benefit!$H$9 / CEA!$C$7) * oppcost!E4 -> -2812.7847 | G15: =benefit!F10 - ($B15 * benefit!$H$9 / CEA!$C$7) * oppcost!F4 -> -2605.0061 | H15: =benefit!G10 - ($B15 * benefit!$H$9 / CEA!$C$7) * oppcost!G4 -> -2423.2546 | I15: =((0.2*(63+(D15/8982727))^(0.5)+0.2*(68+(E15/9687031))^(0.5)+0.2*(70+(F15/9744766))^(0.5)+0.2*(73+(G15/9530611))^(0.5)+0.2*(75+(H15/9275464))^(0.5))^(1/0.5))-69.784581 -> -0.047933167 | J15: =IF(I15>0, "semaglutide", "baseline") -> baseline
B18: SA2 — Opportunity Cost Distribution (base case: equal / pro-rata 20% each quintile)
B20: Scenario | C20: Q1 Share | D20: Q2 Share | E20: Q3 Share | F20: Q4 Share | G20: Q5 Share | H20: Total net benefit | I20: Q1's net benefit | J20: Q1 outcome
B21: Equal (base case) ← base case | C21: 0.2 | D21: 0.2 | E21: 0.2 | F21: 0.2 | G21: 0.2 | H21: {=SUM( benefit!C$10:G$10 - ($B$8*benefit!$H$9/CEA!$C$7)*C21:G21 )} -> 273.57496 | I21: =benefit!C10 - ($B$8*benefit!$H$9/CEA!$C$7)*C21 -> -210.55585 | J21: =IF(I21<0,"Q1 loses","Q1 gains") -> Q1 loses
B22: Realistic Share (Scenario 2) | C22: 0.2437 | D22: 0.2115 | E22: 0.2151 | F22: 0.1756 | G22: 0.1541 | H22: {=SUM( benefit!C$10:G$10 - ($B$8*benefit!$H$9/CEA!$C$7)*C22:G22 )} -> 273.57496 | I22: =benefit!C11 - ($B$8*benefit!$H$9/CEA!$C$7)*C22 -> -297.32317 | J22: =IF(I22<0,"Q1 loses","Q1 gains") -> Q1 loses
B23: Concentrated poorest | C23: 0.5 | D23: 0.25 | E23: 0.15 | F23: 0.07 | G23: 0.03 | H23: {=SUM( benefit!C$10:G$10 - ($B$8*benefit!$H$9/CEA!$C$7)*C23:G23 )} -> 273.57496 | I23: =benefit!C12 - ($B$8*benefit!$H$9/CEA!$C$7)*C23 -> -610.01882 | J23: =IF(I23<0,"Q1 loses","Q1 gains") -> Q1 loses
B24: Concentrated richest | C24: 0.03 | D24: 0.07 | E24: 0.15 | F24: 0.25 | G24: 0.5 | H24: {=SUM( benefit!C$10:G$10 - ($B$8*benefit!$H$9/CEA!$C$7)*C24:G24 )} -> 273.57496 | I24: =benefit!C13 - ($B$8*benefit!$H$9/CEA!$C$7)*C24 -> -36.601129 | J24: =IF(I24<0,"Q1 loses","Q1 gains") -> Q1 loses
B27: SA3 — Opportunity Cost Threshold (base case: £20,000)
B29: Scenario | C29: Q1 NB | D29: Q2 NB | E29: Q3 NB | F29: Q4 NB | G29: Q5 NB | H29: Total net benefit | I29: Q1 net benefit | J29: Q1 outcome
B30: £20,000 (NICE) | C30: =benefit!C$10 - ($B$8*benefit!$H$9/CEA!$C$7)*oppcost!C$4 -> -210.55585 | D30: =benefit!D$10 - ($B$8*benefit!$H$9/CEA!$C$7)*oppcost!D$4 -> -87.368238 | E30: =benefit!E$10 - ($B$8*benefit!$H$9/CEA!$C$7)*oppcost!E$4 -> -8.6032169 | F30: =benefit!F$10 - ($B$8*benefit!$H$9/CEA!$C$7)*oppcost!F$4 -> 199.17541 | G30: =benefit!G$10 - ($B$8*benefit!$H$9/CEA!$C$7)*oppcost!G$4 -> 380.92686 | H30: =SUM(C30:G30) -> 273.57496 | I30: =C30 -> -210.55585 | J30: =IF(C30<0,"Q1 loses","Q1 gains") -> Q1 loses
B31: £12,936 (Claxton empirical) | C31: =benefit!C$10 - ($B$8*benefit!$H$9/CEA!$C$8)*oppcost!C$4 -> -343.80177 | D31: =benefit!D$10 - ($B$8*benefit!$H$9/CEA!$C$8)*oppcost!D$4 -> -220.61416 | E31: =benefit!E$10 - ($B$8*benefit!$H$9/CEA!$C$8)*oppcost!E$4 -> -141.84913 | F31: =benefit!F$10 - ($B$8*benefit!$H$9/CEA!$C$8)*oppcost!F$4 -> 65.929496 | G31: =benefit!G$10 - ($B$8*benefit!$H$9/CEA!$C$8)*oppcost!G$4 -> 247.68094 | H31: =SUM(C31:G31) -> -392.65462 | I31: =C31 -> -343.80177 | J31: =IF(C31<0,"Q1 loses","Q1 gains") -> Q1 loses
